README.txt
setup.py
cs/__init__.py
cs.gallery.egg-info/PKG-INFO
cs.gallery.egg-info/SOURCES.txt
cs.gallery.egg-info/dependency_links.txt
cs.gallery.egg-info/entry_points.txt
cs.gallery.egg-info/namespace_packages.txt
cs.gallery.egg-info/not-zip-safe
cs.gallery.egg-info/paster_plugins.txt
cs.gallery.egg-info/requires.txt
cs.gallery.egg-info/top_level.txt
cs/gallery/__init__.py
cs/gallery/configure.zcml
cs/gallery/tests.py
cs/gallery/profiles/default/cssregistry.xml
cs/gallery/profiles/default/jsregistry.xml
cs/gallery/resources/closelabel.gif
cs/gallery/resources/loading.gif
cs/gallery/resources/nextlabel.gif
cs/gallery/resources/prevlabel.gif
cs/gallery/resources/slimbox2.css
cs/gallery/resources/slimbox2.js
docs/HISTORY.txt
docs/INSTALL.txt
docs/LICENSE.GPL
docs/LICENSE.txt