Metadata-Version: 1.1
Name: cs.gallery
Version: 1.0
Summary: Simple product to add slimbox library to your Plone Site
Home-page: http://svn.plone.org/svn/plone/plone.example
Author: Mikel Larreategi
Author-email: mlarreategi@codesyntax.com
License: GPL
Platform: UNKNOWN
Classifier: Framework :: Plone
Classifier: Programming Language :: Python
